{"commitInfo":{"timestamp":1758187817773,"operation":"MERGE","operationParameters":{"predicate":"[\"(supplier_id#4684 = supplier_id#4692)\"]","matchedPredicates":"[{\"actionType\":\"update\"}]","notMatchedPredicates":"[{\"actionType\":\"insert\"}]","notMatchedBySourcePredicates":"[]"},"readVersion":5,"isolationLevel":"Serializable","isBlindAppend":false,"operationMetrics":{"numTargetRowsCopied":"0","numTargetRowsDeleted":"0","numTargetBytesRemoved":"0","numTargetDeletionVectorsAdded":"0","numTargetRowsMatchedUpdated":"0","numTargetRowsMatchedDeleted":"0","numTargetRowsUpdated":"0","numTargetChangeFilesAdded":"0","numTargetRowsNotMatchedBySourceDeleted":"0","rewriteTimeMs":"61","numTargetFilesAdded":"1","numTargetBytesAdded":"1861","executionTimeMs":"875","materializeSourceTimeMs":"357","numTargetRowsInserted":"4","numTargetDeletionVectorsUpdated":"0","scanTimeMs":"455","numOutputRows":"4","numTargetDeletionVectorsRemoved":"0","numTargetRowsNotMatchedBySourceUpdated":"0","numSourceRows":"4","numTargetFilesRemoved":"0"},"engineInfo":"Apache-Spark/4.0.0 Delta-Lake/4.0.0","txnId":"bb11827b-02f7-4a7f-849b-d65337395ced"}}
{"add":{"path":"part-00000-3513e0d9-4fb5-417e-a957-6b378a6efdb7-c000.snappy.parquet","partitionValues":{},"size":1861,"modificationTime":1758187817770,"dataChange":true,"stats":"{\"numRecords\":4,\"minValues\":{\"supplier_id\":\"1\",\"supplier_name\":\"Everest Traders\",\"source_file\":\"suppliers.csv\",\"imported_date\":\"2025-09-18T06:33:38.995+05:45\",\"rn\":1},\"maxValues\":{\"supplier_id\":\"4\",\"supplier_name\":\"Sagarmatha Distributors\",\"source_file\":\"suppliers.csv\",\"imported_date\":\"2025-09-18T06:33:38.995+05:45\",\"rn\":1},\"nullCount\":{\"supplier_id\":0,\"supplier_name\":0,\"source_file\":0,\"imported_date\":0,\"rn\":0}}"}}
