{"commitInfo":{"timestamp":1758181295958,"operation":"CREATE TABLE","operationParameters":{"partitionBy":"[]","clusterBy":"[]","description":null,"isManaged":"false","properties":"{}"},"isolationLevel":"Serializable","isBlindAppend":true,"operationMetrics":{},"engineInfo":"Apache-Spark/4.0.0 Delta-Lake/4.0.0","txnId":"ba07b105-100b-4239-828b-2c897aae42cb"}}
{"metaData":{"id":"9135290f-bcd6-4b6f-800e-3d0f86b4185e","format":{"provider":"parquet","options":{}},"schemaString":"{\"type\":\"struct\",\"fields\":[{\"name\":\"date_sk\",\"type\":\"integer\",\"nullable\":true,\"metadata\":{}},{\"name\":\"full_date\",\"type\":\"date\",\"nullable\":true,\"metadata\":{}},{\"name\":\"day\",\"type\":\"integer\",\"nullable\":true,\"metadata\":{}},{\"name\":\"month\",\"type\":\"integer\",\"nullable\":true,\"metadata\":{}},{\"name\":\"year\",\"type\":\"integer\",\"nullable\":true,\"metadata\":{}},{\"name\":\"quarter\",\"type\":\"integer\",\"nullable\":true,\"metadata\":{}},{\"name\":\"day_name\",\"type\":\"string\",\"nullable\":true,\"metadata\":{}},{\"name\":\"month_name\",\"type\":\"string\",\"nullable\":true,\"metadata\":{}},{\"name\":\"is_weekend\",\"type\":\"boolean\",\"nullable\":true,\"metadata\":{}}]}","partitionColumns":[],"configuration":{},"createdTime":1758181295946}}
{"protocol":{"minReaderVersion":1,"minWriterVersion":2}}
